littlecsv/__init__.py
littlecsv/cli.py
littlecsv/header.py
littlecsv/main.py
littlecsv/utils.py
littlecsv-1.0.5.dist-info/licenses/LICENCE
littlecsv-1.0.5.dist-info/METADATA
littlecsv-1.0.5.dist-info/WHEEL
littlecsv-1.0.5.dist-info/entry_points.txt
littlecsv-1.0.5.dist-info/top_level.txt
littlecsv-1.0.5.dist-info/RECORD
