Metadata-Version: 2.4
Name: littlecsv
Version: 1.0.5
Summary: Simple, light and little pip package to read, write and manage CSV files ('.csv') in Python.
Home-page: https://github.com/MatsveiTsishyn/littlecsv
Author: Matsvei Tsishyn
Author-email: Matsvei Tsishyn <matsvei.tsishyn@protonmail.com>
License-Expression: MIT
Project-URL: Homepage, https://github.com/MatsveiTsishyn/littlecsv
Classifier: Programming Language :: Python :: 3
Classifier: Operating System :: OS Independent
Requires-Python: >=3.9
License-File: LICENCE
Requires-Dist: numpy
Dynamic: author
Dynamic: home-page
Dynamic: license-file
Dynamic: requires-python
